{"api_built-in_fs.md":"CTeg9mCk","api_index.md":"Yi6MbETn","api_modules_commands.md":"CaDEct7D","api_modules_dialog.md":"B2TJuU7f","api_modules_file.md":"BU308eWz","api_modules_history.md":"DMph_RNt","api_modules_hooks.md":"C_PBAXdq","api_modules_hotkeys.md":"VYK8Ncgy","api_modules_invoke.md":"DTfPT2pE","api_modules_menubar.md":"CVcFufxO","api_modules_ui.md":"DQXahPK2","api_modules_util.md":"DHjW-BSU","docs.md":"Bqqe-vEC","docs_agent-commands.md":"DYm_QHob","docs_commands.md":"DYEAWh4X","docs_concepts.md":"yl2iyH55","docs_extensions.md":"m_YhcJr3","docs_menubar.md":"BNTcduiY","docs_publishing-extensions.md":"DstwSCAt","index.md":"BptnUme2","install.md":"C5PbyP5n"}
